{"reponsecode": 0, "reponsemessage": "", "data": {"exhibit_id": "ahbwysjy_museum_xgdx_ugvk", "exhibition_name": "安徽文明史陈列（一）", "location": "0,0", "name": "楚地半天下", "size": "", "like": 0, "share_url": "mob/exhibit/detail?exhibit_id=3408", "is_favorited": 0, "_3d_url": "", "description": "三千六百多年前，也就是中国商代初期，一支衣衫褴褛、疲惫不堪的的队伍艰难的从黄河流域向长江流域迁徙，他们就是楚人的祖先，他们在这里“荜路蓝缕，以启山林”，艰难地伐掉巨木，征服丘陵，开垦出一块又一块农田。谁也不会先到，这样一支队伍，会在今后的数百年间，建立了一个强大的诸侯国——楚国。楚国到了楚庄王时期，由于任用贤臣，励精图治，开创属于楚国鼎盛的时期。那个时候的楚国疆土西起大巴山、巫山、武陵山，东至大海，南起南岭，北至今河南中部、安徽和江苏北部、陕西东南部、山东西南部，幅员广阔，有着“楚地半天下”的说法。", "images": ["content/fileroot/museum/ahbwysjy_museum/image/KUWIgti9pB_s.webp", "content/fileroot/museum/ahbwysjy_museum/image/3KiBwZb4r1_s.webp"], "audio": [], "video": {"videourl": "", "img": ""}, "ispaid": 1}}