{"reponsecode": 0, "reponsemessage": "", "data": {"exhibit_id": "ahbwysjy_museum_xgdx_sskh", "exhibition_name": "安徽文明史陈列（一）", "location": "0,0", "name": "朱漆木碗", "size": "", "like": 0, "share_url": "mob/exhibit/detail?exhibit_id=3428", "is_favorited": 0, "_3d_url": "", "description": "大家看到这个小小的木碗可能并没有那么精致，但是它的来头可不小，它是浙江博物馆的当红明星，也是国家首批禁止出境展览的国宝之一！这是一只来自河姆渡时期的木碗，距今已经有七千多年的历史了。更让人惊奇的是，这件小小木碗上还有一层薄薄的红色涂料，经过科学测定，这种朱红色的涂料就是“漆”。这事儿可了不得了，轰动一时。河姆渡朱漆木碗的出现把我国使用生漆的历史提早到了7000年前，从而进一步证明，我国是世界上最早使用天然“漆”的国家。|古代的漆是在漆树上割开口子，从中提取的，通常天然漆和空气接触后，会固化成黑色的硬膜。但这只漆碗分明是红色的，说明河姆渡人已经学会在天然漆中添加矿物颜料。这一定是在长期的生产和生活中积累了丰富的经验后才可能实现的。说明至少在六、七千年之前，我们的先民已将天然漆用于装饰生活器具的表面。", "images": ["content/fileroot/museum/ahbwysjy_museum/image/Se5Kh4YqXk_s.webp", "content/fileroot/museum/ahbwysjy_museum/image/2d9A2oKnpw_s.webp", "content/fileroot/museum/ahbwysjy_museum/image/zlPCFK5Om9_s.webp", "content/fileroot/museum/ahbwysjy_museum/image/LVYXtd7EsX_s.webp", "content/fileroot/museum/ahbwysjy_museum/image/EEB72X8QXP_s.webp"], "audio": [], "video": {"videourl": "", "img": ""}, "ispaid": 1}}